easylatex/__init__.py
easylatex/core.py
easylatex-0.1.0.dist-info/LICENSE
easylatex-0.1.0.dist-info/METADATA
easylatex-0.1.0.dist-info/WHEEL
easylatex-0.1.0.dist-info/top_level.txt
easylatex-0.1.0.dist-info/RECORD
