Metadata-Version: 2.1
Name: easylatex
Version: 0.1.0
Summary: Simplify writing LaTeX documents with Python.
Home-page: 
Author: Sagar Paul
Author-email: sagarpaul.dev@gmail.com
Classifier: Programming Language :: Python :: 3
Classifier: License :: OSI Approved :: MIT License
Classifier: Operating System :: OS Independent
Requires-Python: >=3.6
License-File: LICENSE
